SongBloom/__init__.py
SongBloom/g2p/__init__.py
SongBloom/g2p/lyric_common.py
SongBloom/g2p/cn_zh_g2p/__init__.py
SongBloom/g2p/cn_zh_g2p/chinese.py
SongBloom/g2p/cn_zh_g2p/cmudict-fast.rep
SongBloom/g2p/cn_zh_g2p/cmudict.rep
SongBloom/g2p/cn_zh_g2p/engdict-hot.rep
SongBloom/g2p/cn_zh_g2p/engdict_cache.pickle
SongBloom/g2p/cn_zh_g2p/english.py
SongBloom/g2p/cn_zh_g2p/opencpop-strict.txt
SongBloom/g2p/cn_zh_g2p/symbols.py
SongBloom/g2p/cn_zh_g2p/tone_sandhi.py
SongBloom/g2p/cn_zh_g2p/nltk_data/taggers/averaged_perceptron_tagger/averaged_perceptron_tagger.pickle
SongBloom/g2p/cn_zh_g2p/zh_normalization/README.md
SongBloom/g2p/cn_zh_g2p/zh_normalization/__init__.py
SongBloom/g2p/cn_zh_g2p/zh_normalization/char_convert.py
SongBloom/g2p/cn_zh_g2p/zh_normalization/chronology.py
SongBloom/g2p/cn_zh_g2p/zh_normalization/constants.py
SongBloom/g2p/cn_zh_g2p/zh_normalization/num.py
SongBloom/g2p/cn_zh_g2p/zh_normalization/phonecode.py
SongBloom/g2p/cn_zh_g2p/zh_normalization/quantifier.py
SongBloom/g2p/cn_zh_g2p/zh_normalization/text_normlization.py
SongBloom/g2p/pinyin/__init__.py
SongBloom/g2p/pinyin/pinyin.py
SongBloom/g2p/pinyin/symbols.py
SongBloom/models/transformer.py
SongBloom/models/base/sample.py
SongBloom/models/base/utils.py
SongBloom/models/musicgen/__init__.py
SongBloom/models/musicgen/get_backend.py
SongBloom/models/musicgen/conditioners/__init__.py
SongBloom/models/musicgen/conditioners/base.py
SongBloom/models/musicgen/conditioners/text.py
SongBloom/models/musicgen/conditioners/wav.py
SongBloom/models/musicgen/modules/streaming.py
SongBloom/models/musicldm/__init__.py
SongBloom/models/musicldm/musicldm_dit.py
SongBloom/models/musicldm/inference/__init__.py
SongBloom/models/musicldm/inference/sampling.py
SongBloom/models/songbloom/songbloom_mvsa.py
SongBloom/models/songbloom/songbloom_pl.py
SongBloom/models/vae_frontend/__init__.py
SongBloom/models/vae_frontend/autoencoders.py
SongBloom/models/vae_frontend/bottleneck.py
tts_webui_songbloom-0.1.1.dist-info/licenses/LICENSE
tts_webui_songbloom-0.1.1.dist-info/METADATA
tts_webui_songbloom-0.1.1.dist-info/WHEEL
tts_webui_songbloom-0.1.1.dist-info/top_level.txt
tts_webui_songbloom-0.1.1.dist-info/RECORD
