Metadata-Version: 2.4
Name: tts-webui.songbloom
Version: 0.1.1
Summary: SongBloom package for tts-webui
Author: Your Name
License: MIT License
Project-URL: Homepage, https://github.com/rsxdalv/tts-webui.songbloom
Classifier: Programming Language :: Python :: 3
Classifier: License :: OSI Approved :: MIT License
Classifier: Operating System :: OS Independent
Requires-Python: >=3.8
License-File: LICENSE
Requires-Dist: huggingface-hub>=0.24.6
Requires-Dist: jieba-fast>=0.53
Requires-Dist: pypinyin>=0.51.0
Requires-Dist: cn2an>=0.5.22
Requires-Dist: wordsegment>=1.3.1
Requires-Dist: g2p-en>=2.1.0
Requires-Dist: lightning>=2.2.1
Requires-Dist: nltk>=3.8.1
Requires-Dist: omegaconf>=2.2.0
Requires-Dist: torch>=2.2.0
Requires-Dist: torchaudio>=2.2.0
Requires-Dist: transformers>=4.44.1
Requires-Dist: einops>=0.8.0
Requires-Dist: spacy>=3.7.4
Requires-Dist: num2words>=0.5.13
Requires-Dist: descript-audio-codec>=1.0.0
Requires-Dist: vector_quantize_pytorch>=1.14.8
Dynamic: license-file
